procslink/__init__.py
procslink/common.py
procslink/jsonrpc.py
procslink/netlink.py
procslink/procslink.py
procslink-0.1.2.dist-info/DESCRIPTION.rst
procslink-0.1.2.dist-info/METADATA
procslink-0.1.2.dist-info/RECORD
procslink-0.1.2.dist-info/WHEEL
procslink-0.1.2.dist-info/metadata.json
procslink-0.1.2.dist-info/top_level.txt
